[{"name":"value-box-core","version":"0.6.2","src":{"file":"\/home\/jmachiine\/R\/x86_64-pc-linux-gnu-library\/4.4\/flexdashboard\/www\/flex_dashboard"},"meta":null,"script":null,"stylesheet":"value-box.css","head":null,"attachment":null,"all_files":true},{"name":"font-awesome","version":"6.4.2","src":{"file":"\/home\/jmachiine\/R\/x86_64-pc-linux-gnu-library\/4.4\/fontawesome\/fontawesome"},"meta":null,"script":null,"stylesheet":["css\/all.min.css","css\/v4-shims.min.css"],"head":null,"attachment":null,"all_files":true}]
